jet_sidebar/__init__.py
jet_sidebar/apps.py
jet_sidebar/settings.py
jet_sidebar/locale/pt_BR/LC_MESSAGES/django.mo
jet_sidebar/locale/pt_BR/LC_MESSAGES/django.po
jet_sidebar/migrations/__init__.py
jet_sidebar/static/admin/css/charsleft.css
jet_sidebar/static/admin/css/dashboard_custom.css
jet_sidebar/static/admin/css/jet_customization.css
jet_sidebar/static/admin/css/bootstrap/bootstrap.css
jet_sidebar/static/admin/css/bootstrap/bootstrap.css.map
jet_sidebar/static/admin/css/bootstrap/bootstrap.min.css
jet_sidebar/static/admin/css/bootstrap/bootstrap.min.css.map
jet_sidebar/static/admin/js/admin.mask.js
jet_sidebar/static/admin/js/charsleft.js
jet_sidebar/static/admin/js/jquery.init.js
jet_sidebar/static/admin/js/jquery.mask.min.js
jet_sidebar/static/admin/js/bootstrap/bootstrap.bundle.js
jet_sidebar/static/admin/js/bootstrap/bootstrap.bundle.js.map
jet_sidebar/static/admin/js/bootstrap/bootstrap.bundle.min.js
jet_sidebar/static/admin/js/bootstrap/bootstrap.bundle.min.js.map
jet_sidebar/static/admin/js/bootstrap/bootstrap.js
jet_sidebar/static/admin/js/bootstrap/bootstrap.js.map
jet_sidebar/static/admin/js/bootstrap/bootstrap.min.js
jet_sidebar/static/admin/js/bootstrap/bootstrap.min.js.map
jet_sidebar/static/admin/sidebar/css/sidebar.css
jet_sidebar/static/admin/sidebar/js/sidebar.js
jet_sidebar/templates/admin/_menu_sidebar.html
jet_sidebar/templates/admin/base.html
jet_sidebar/templatetags/__init__.py
jet_sidebar/templatetags/jet_rebuild_tags.py
jet_sidebar/templatetags/__pycache__/__init__.cpython-37.pyc
jet_sidebar/templatetags/__pycache__/jet_rebuild_tags.cpython-37.pyc
jet_sidebar-0.2.7.dist-info/LICENSE
jet_sidebar-0.2.7.dist-info/METADATA
jet_sidebar-0.2.7.dist-info/WHEEL
jet_sidebar-0.2.7.dist-info/top_level.txt
jet_sidebar-0.2.7.dist-info/RECORD
