Metadata-Version: 2.1
Name: jet-sidebar
Version: 0.2.7
Summary: Este pacote é uma modificação para o Django Jet
Home-page: https://github.com/raifran1/jet-sidebar
Author: Raifran Lucas
Author-email: contato@raifranlucas.dev
License: UNKNOWN
Project-URL: Bug Tracker, https://github.com/raifran1/jet-sidebar/issues
Platform: UNKNOWN
Classifier: Framework :: Django
Classifier: Programming Language :: Python :: 2.6
Classifier: Programming Language :: Python :: 2.7
Classifier: Programming Language :: Python :: 3.7
Classifier: License :: OSI Approved :: MIT License
Classifier: Environment :: Web Environment
Classifier: Operating System :: OS Independent
Requires-Python: >=2.6
License-File: LICENSE
